libtesthello/__init__.py
libtesthello/hello.py
libtesthello-0.0.3.dist-info/LICENSE
libtesthello-0.0.3.dist-info/METADATA
libtesthello-0.0.3.dist-info/WHEEL
libtesthello-0.0.3.dist-info/top_level.txt
libtesthello-0.0.3.dist-info/RECORD
