Metadata-Version: 2.1
Name: libtesthello
Version: 0.0.3
Summary: Biblioteca que diz Hello
Home-page: https://github.com/faustoroger/dio-desafio-github-primeiro-repositorio/tree/main/Python/Desafios/03-Desafios.Descomplicando.a.Cria%C3%A7%C3%A3o.de.Pacotes/libtesthello
Author: fr
Author-email: testsayhellofr@gmail.com
License: MIT
Platform: UNKNOWN
License-File: LICENSE
Requires-Dist: colorama (==0.4.4)
Requires-Dist: termcolor (==1.1.0)
